README.md
setup.py
chinapay/__init__.py
chinapay/component.py
chinapay/constants.py
chinapay/events.py
chinapay/exceptions.py
chinapay/fields.py
chinapay/messages.py
chinapay/parser.py
chinapay/replies.py
chinapay/utils.py
chinapay.egg-info/PKG-INFO
chinapay.egg-info/SOURCES.txt
chinapay.egg-info/dependency_links.txt
chinapay.egg-info/requires.txt
chinapay.egg-info/top_level.txt
chinapay/client/__init__.py
chinapay/client/base.py
chinapay/client/api/__init__.py
chinapay/client/api/base.py
chinapay/client/api/card.py
chinapay/client/api/customservice.py
chinapay/client/api/datacube.py
chinapay/client/api/device.py
chinapay/client/api/group.py
chinapay/client/api/invoice.py
chinapay/client/api/jsapi.py
chinapay/client/api/material.py
chinapay/client/api/media.py
chinapay/client/api/menu.py
chinapay/client/api/message.py
chinapay/client/api/misc.py
chinapay/client/api/poi.py
chinapay/client/api/qrcode.py
chinapay/client/api/scan.py
chinapay/client/api/semantic.py
chinapay/client/api/shakearound.py
chinapay/client/api/tag.py
chinapay/client/api/template.py
chinapay/client/api/user.py
chinapay/client/api/wifi.py
chinapay/client/api/wxa.py
chinapay/client/api/merchant/__init__.py
chinapay/client/api/merchant/category.py
chinapay/client/api/merchant/common.py
chinapay/client/api/merchant/express.py
chinapay/client/api/merchant/group.py
chinapay/client/api/merchant/order.py
chinapay/client/api/merchant/shelf.py
chinapay/client/api/merchant/stock.py
chinapay/crypto/__init__.py
chinapay/crypto/base.py
chinapay/crypto/cryptography.py
chinapay/crypto/pkcs7.py
chinapay/crypto/pycrypto.py
chinapay/enterprise/__init__.py
chinapay/enterprise/crypto.py
chinapay/enterprise/events.py
chinapay/enterprise/exceptions.py
chinapay/enterprise/messages.py
chinapay/enterprise/parser.py
chinapay/enterprise/replies.py
chinapay/enterprise/client/__init__.py
chinapay/enterprise/client/api/__init__.py
chinapay/enterprise/client/api/agent.py
chinapay/enterprise/client/api/batch.py
chinapay/enterprise/client/api/chat.py
chinapay/enterprise/client/api/department.py
chinapay/enterprise/client/api/jsapi.py
chinapay/enterprise/client/api/material.py
