Metadata-Version: 1.0
Name: chinapay
Version: 0.0.1
Summary: chinapay python sdk
Home-page: UNKNOWN
Author: liupeng
Author-email: liupeng.dalian@gmail.com
License: MIT License
Keywords: chinapay,pay
Platform: any
